meikiocr/__init__.py
meikiocr/cli.py
meikiocr/ocr.py
meikiocr-0.2.0.dist-info/licenses/LICENSE
meikiocr-0.2.0.dist-info/METADATA
meikiocr-0.2.0.dist-info/WHEEL
meikiocr-0.2.0.dist-info/entry_points.txt
meikiocr-0.2.0.dist-info/top_level.txt
meikiocr-0.2.0.dist-info/RECORD
