Metadata-Version: 2.4
Name: meikiocr
Version: 0.2.0
Summary: High-speed, high-accuracy, local OCR for Japanese video games.
Author: rtr46
License-Expression: Apache-2.0
Project-URL: Homepage, https://github.com/rtr46/meikiocr
Project-URL: Bug Tracker, https://github.com/rtr46/meikiocr/issues
Project-URL: Hugging Face, https://huggingface.co/spaces/rtr46/meikiocr
Classifier: Programming Language :: Python :: 3
Classifier: Operating System :: OS Independent
Classifier: Topic :: Scientific/Engineering :: Image Recognition
Requires-Python: >=3.8
License-File: LICENSE
Requires-Dist: numpy
Requires-Dist: opencv-python-headless
Requires-Dist: huggingface-hub
Requires-Dist: onnxruntime
Dynamic: license-file
